cosian/__init__.py
cosian-0.0.1.dist-info/METADATA
cosian-0.0.1.dist-info/WHEEL
cosian-0.0.1.dist-info/top_level.txt
cosian-0.0.1.dist-info/RECORD
